deskaone_sdk_scrypt_v2/__init__.py
deskaone_sdk_scrypt_v2/AntiCaptcha/__init__.py
deskaone_sdk_scrypt_v2/Client/__init__.py
deskaone_sdk_scrypt_v2/Database/__init__.py
deskaone_sdk_scrypt_v2/Exceptions/__init__.py
deskaone_sdk_scrypt_v2/Internal/__init__.py
deskaone_sdk_scrypt_v2/Internal/API.py
deskaone_sdk_scrypt_v2/Internal/Internal.py
deskaone_sdk_scrypt_v2/Utils/__init__.py
deskaone_sdk_scrypt_v2/Utils/AWSRequestsAuth.py
deskaone_sdk_scrypt_v2/Utils/Color.py
deskaone_sdk_scrypt_v2/Utils/Crypto.py
deskaone_sdk_scrypt_v2/Utils/ProgressBar.py
deskaone_sdk_scrypt_v2/Utils/Reset.py
deskaone_sdk_scrypt_v2/Utils/Timer.py
deskaone_sdk_scrypt_v2/Utils/Typer.py
deskaone_sdk_scrypt_v2/Utils/UserAgent.py
deskaone_sdk_scrypt_v2/Version.py
deskaone_sdk_scrypt_v2-1.0.6.dist-info/WHEEL
deskaone_sdk_scrypt_v2-1.0.6.dist-info/METADATA
deskaone_sdk_scrypt_v2-1.0.6.dist-info/RECORD
